{
    "os": "Linux-3.10.0-1160.31.1.el7.x86_64-x86_64-with-glibc2.2.5",
    "python": "3.8.5",
    "heartbeatAt": "2021-12-19T10:17:29.482606",
    "startedAt": "2021-12-19T10:17:28.144604",
    "docker": null,
    "gpu": "GeForce RTX 2080 Ti",
    "gpu_count": 2,
    "cpu_count": 72,
    "cuda": null,
    "args": [
        "--config=config/cifar100_cfg.py",
        "--config.save_dir=/cluster/scratch/rarade/common_corruptions/PRIME/c100_prime_01/"
    ],
    "state": "running",
    "program": "train.py",
    "codePath": "train.py",
    "host": "eu-g2-20",
    "username": "rarade",
    "executable": "/cluster/home/rarade/torch/bin/python"
}
